<?xml version="1.0" encoding="UTF-8" standalone="no"?>
<ACGDataFile>
<alignment>
<labels>i13227
i84399
i73343
i56568
i34131
i18428
i33911
i87409
i30170
i71025
i50645
i56491
i56238
i68045
i30931
i41931
i28711
i43815
i26047
i44680
i73247
i41067
i91030
i39180
i10001
i64260
i34693
i82766
i75127
i71485
i65249
i31023
i30826
i77078
i62899
i42687
i44589
i69082
i71572
i70237
i38158
i39325
i70025
i12286
i78729
i50264
i51343
i75904
i53310
i68291
i83805
i36103
i16569
i48067
i89567
i54414
i73403
i30389
i54629
i96150
i45557
i91442
i42960
i45447
i28280
i88542
i20975
i78287
i41028
i25326
i71148
i60385
i41581
i25318
i37137
i30019
i19111
i70473
i50595
i19407
i40418
i63298
i65984
i22277
i89126
i47498
i76280
i56911
i86256
i10115
i12541
i67671
i53094
i31640
i14448
i82540
i36178
i32792
i62193
i21136
</labels>
<columnmap>0,0,1,2,3,1,2,3,2,1,2,0,2,2,2,0,2,1,3,0,2,0,0,1,2,1,2,2,1,0,3,3,2,3,1,0,3,0,1,0,1,4,0,2,2,2,0,3,3,1,0,5,3,0,3,1,1,2,2,0,2,1,0,1,1,3,1,2,3,1,3,3,2,3,2,1,2,2,0,3,0,0,3,1,3,3,0,1,1,0,0,2,0,2,2,0,6,1,0,0,2,3,1,1,2,1,3,2,2,2,7,8,3,0,3,0,3,3,1,0,0,0,3,2,2,2,0,3,9,1,0,3,1,10,2,0,1,1,2,3,0,0,2,11,1,0,0,0,3,1,3,2,2,0,1,3,1,1,0,2,0,3,3,1,2,2,0,2,2,2,3,0,1,3,0,0,2,1,12,3,0,1,0,1,0,3,1,13,3,2,3,3,0,1,0,1,1,2,2,1,0,14,15,0,2,1,3,0,16,1,2,1,3,0,1,0,2,3,3,3,3,2,1,0,1,0,1,3,2,0,1,0,1,17,2,1,18,2,3,0,19,3,2,3,20,3,2,2,0,2,1,1,0,2,0,3,3,3,3,0,0,2,3,3,1,0,1,2,3,2,2,1,1,1,0,1,2,3,2,0,0,0,2,1,2,1,0,1,2,3,3,0,3,3,0,3,1,1,3,1,2,21,2,2,3,1,0,0,2,2,1,0,1,1,1,2,0,3,2,2,1,0,2,22,0,0,0,0,2,3,1,0,2,1,3,3,1,2,2,3,2,1,0,0,1,3,1,2,3,2,1,0,0,3,0,0,3,3,3,1,23,0,2,1,0,1,0,1,3,3,1,1,3,0,2,1,1,2,1,1,3,3,1,1,1,3,3,0,24,2,1,3,2,2,0,0,1,2,1,3,2,1,25,3,1,26,0,1,3,1,1,2,1,1,3,0,1,0,2,3,0,0,2,0,0,3,1,1,1,0,0,0,0,0,2,2,2,0,2,0,3,0,3,0,3,1,27,3,1,2,2,3,1,1,0,1,2,0,0,1,3,3,2,2,2,3,1,0,0,1,1,3,0,2,2,2,1,1,0,2,2,0,1,3,2,3,2,3,1,1,28,3,2,2,1,1,1,1,1,0,</columnmap>
<columns>
<column index="0">2,2,2,2,2,2,2,2,2,2,2,2,2,2,2,2,2,2,2,2,2,2,2,2,2,2,2,2,2,2,2,2,2,2,2,2,2,2,2,2,2,2,2,2,2,2,2,2,2,2,2,2,2,2,2,2,2,2,2,2,2,2,2,2,2,2,2,2,2,2,2,2,2,2,2,2,2,2,2,2,2,2,2,2,2,2,2,2,2,2,2,2,2,2,2,2,2,2,2,2,</column>
<column index="1">0,0,0,0,0,0,0,0,0,0,0,0,0,0,0,0,0,0,0,0,0,0,0,0,0,0,0,0,0,0,0,0,0,0,0,0,0,0,0,0,0,0,0,0,0,0,0,0,0,0,0,0,0,0,0,0,0,0,0,0,0,0,0,0,0,0,0,0,0,0,0,0,0,0,0,0,0,0,0,0,0,0,0,0,0,0,0,0,0,0,0,0,0,0,0,0,0,0,0,0,</column>
<column index="2">3,3,3,3,3,3,3,3,3,3,3,3,3,3,3,3,3,3,3,3,3,3,3,3,3,3,3,3,3,3,3,3,3,3,3,3,3,3,3,3,3,3,3,3,3,3,3,3,3,3,3,3,3,3,3,3,3,3,3,3,3,3,3,3,3,3,3,3,3,3,3,3,3,3,3,3,3,3,3,3,3,3,3,3,3,3,3,3,3,3,3,3,3,3,3,3,3,3,3,3,</column>
<column index="3">1,1,1,1,1,1,1,1,1,1,1,1,1,1,1,1,1,1,1,1,1,1,1,1,1,1,1,1,1,1,1,1,1,1,1,1,1,1,1,1,1,1,1,1,1,1,1,1,1,1,1,1,1,1,1,1,1,1,1,1,1,1,1,1,1,1,1,1,1,1,1,1,1,1,1,1,1,1,1,1,1,1,1,1,1,1,1,1,1,1,1,1,1,1,1,1,1,1,1,1,</column>
<column index="4">2,2,2,2,2,0,2,2,2,2,2,2,2,2,2,0,2,2,2,0,2,2,0,2,2,2,2,2,2,2,0,2,2,2,2,2,2,2,2,2,2,2,2,2,2,2,2,2,2,2,2,2,2,2,2,2,0,2,2,2,2,2,2,2,2,2,2,2,2,2,0,2,0,2,2,2,0,2,2,2,2,2,2,0,2,2,2,2,2,2,2,2,2,0,2,2,2,2,2,2,</column>
<column index="5">3,2,2,3,3,2,2,3,2,2,3,3,2,2,3,2,3,3,3,2,3,2,2,3,3,3,3,2,3,3,2,3,2,3,3,3,3,2,3,2,3,3,3,3,3,2,3,3,2,2,2,3,3,3,2,2,2,3,2,2,3,3,2,3,2,2,3,3,2,3,2,3,2,3,3,3,2,3,2,3,2,3,3,2,3,3,3,2,3,3,3,3,2,2,2,3,2,3,3,3,</column>
<column index="6">0,0,0,2,0,0,0,2,0,0,2,2,0,0,0,0,2,0,2,0,2,0,0,2,2,0,2,0,0,2,0,2,0,2,2,0,2,0,2,0,2,2,2,0,2,0,0,2,0,0,0,0,2,2,0,0,0,0,0,0,2,2,0,2,0,0,0,2,0,0,0,2,0,2,0,2,0,0,0,2,0,2,2,0,2,2,2,0,0,2,2,0,0,0,0,2,0,2,2,0,</column>
<column index="7">3,3,3,3,3,3,3,3,3,3,3,3,3,3,3,3,3,3,3,3,3,3,3,3,3,3,3,3,2,3,3,3,3,3,3,3,3,3,3,3,3,3,3,3,3,3,3,3,3,3,3,2,3,3,3,3,3,3,3,3,3,3,3,3,3,3,2,3,3,3,3,3,3,3,2,3,3,3,3,3,3,3,3,3,3,3,3,3,3,3,3,3,3,3,3,3,3,3,3,3,</column>
<column index="8">2,2,2,2,2,2,2,2,2,2,2,2,2,2,2,2,0,2,2,2,0,2,2,2,2,2,2,2,2,2,2,2,2,2,2,2,2,2,0,2,2,2,2,2,2,2,2,2,2,2,2,2,2,2,2,2,2,2,2,2,2,2,2,2,2,2,2,2,2,2,2,0,2,2,2,2,2,2,2,0,2,2,0,2,2,0,2,2,2,2,2,2,2,2,2,2,2,2,2,2,</column>
<column index="9">2,2,2,2,2,3,2,2,2,2,2,2,2,2,2,3,2,2,2,3,2,2,3,2,2,2,2,2,3,2,3,2,2,2,2,2,2,2,2,2,2,2,2,2,2,2,2,2,2,2,2,3,2,2,2,2,3,2,2,2,2,2,2,2,2,2,3,2,2,2,3,2,3,2,3,2,3,2,2,2,2,2,2,3,2,2,2,2,2,2,2,2,2,3,2,2,2,2,2,2,</column>
<column index="10">1,1,1,1,1,1,1,1,1,1,1,1,1,1,1,1,1,1,1,1,1,1,1,1,1,1,1,1,1,1,1,1,1,1,1,1,1,1,1,1,1,1,1,1,1,1,1,1,1,1,1,1,1,1,1,1,1,1,1,1,1,1,1,1,1,1,1,1,1,1,1,1,1,1,1,1,1,1,1,1,0,1,1,1,1,1,1,1,1,1,1,1,1,1,1,1,1,1,1,1,</column>
<column index="11">0,0,0,0,0,0,2,0,2,2,0,0,0,2,0,0,0,0,0,0,0,0,0,0,0,0,0,0,0,0,0,0,0,0,0,0,0,0,0,0,0,0,0,0,0,2,0,0,0,0,0,0,0,0,0,0,0,0,0,0,0,0,0,0,2,0,0,0,0,0,0,0,0,0,0,0,0,0,2,0,0,0,0,0,0,0,0,0,0,0,0,0,0,0,2,0,0,0,0,0,</column>
<column index="12">1,1,1,1,1,1,1,1,1,1,1,1,1,1,0,1,1,0,1,1,1,1,1,1,1,1,1,1,1,1,1,1,1,1,1,0,1,1,1,1,1,1,1,1,1,1,1,1,1,1,1,1,1,1,1,1,1,1,1,1,1,1,1,1,1,1,1,1,1,0,1,1,1,1,1,1,1,0,1,1,1,1,1,1,1,1,1,1,1,1,1,0,1,1,1,1,1,1,1,0,</column>
<column index="13">0,0,0,0,0,3,0,0,0,0,0,0,0,0,0,3,0,0,0,3,0,0,3,0,0,0,0,0,0,0,3,0,0,0,0,0,0,0,0,0,0,0,0,0,0,0,0,0,0,0,0,0,0,0,0,0,3,0,0,0,0,0,0,0,0,0,0,0,0,0,3,0,3,0,0,0,3,0,0,0,0,0,0,3,0,0,0,0,0,0,0,0,0,3,0,0,0,0,0,0,</column>
<column index="14">2,0,0,0,2,0,0,0,0,0,0,0,0,0,2,0,0,2,0,0,0,0,0,0,0,0,0,0,0,0,0,0,0,0,0,2,0,0,0,0,0,0,0,0,0,0,0,0,0,0,0,0,0,0,0,0,0,2,0,0,0,0,0,0,0,0,0,0,0,2,0,0,0,0,0,0,0,2,0,0,0,0,0,0,0,0,0,0,0,0,0,2,0,0,0,0,0,0,0,2,</column>
<column index="15">0,2,2,0,0,0,0,0,0,0,0,0,2,0,0,0,0,0,0,0,0,0,0,0,0,0,0,0,0,0,0,0,0,0,0,0,0,0,0,2,0,0,0,0,0,0,0,0,2,0,0,0,0,0,2,0,0,0,2,2,0,0,2,0,0,2,0,0,0,0,0,0,0,0,0,0,0,0,0,0,2,0,0,0,0,0,0,0,0,0,0,0,0,0,0,0,2,0,0,0,</column>
<column index="16">1,1,1,3,1,1,1,1,1,1,3,3,1,1,1,1,3,1,3,1,3,1,1,3,3,1,3,1,1,1,1,1,1,3,1,1,3,1,3,1,1,1,3,1,1,1,1,3,1,1,1,1,3,1,1,1,1,1,1,1,3,1,1,3,1,1,1,3,1,1,1,3,1,1,1,3,1,1,1,3,1,3,3,1,3,3,3,1,1,3,3,1,1,1,1,3,1,1,1,1,</column>
<column index="17">3,3,3,3,3,3,3,3,3,3,3,3,3,3,3,3,3,3,3,3,3,3,3,3,3,3,3,3,1,3,3,3,3,3,3,3,3,3,3,3,3,3,3,3,3,3,3,3,3,3,3,1,3,3,3,3,3,3,3,3,3,3,3,3,3,3,1,3,3,3,3,3,3,3,1,3,3,3,3,3,3,3,3,3,3,3,3,3,3,3,3,3,3,3,3,3,3,3,3,3,</column>
<column index="18">3,1,1,1,3,1,1,1,1,1,1,1,1,1,3,1,1,3,1,1,1,1,1,1,1,1,1,1,1,1,1,1,1,1,1,3,1,1,1,1,1,1,1,1,1,1,1,1,1,1,1,1,1,1,1,1,1,3,1,1,1,1,1,1,1,1,1,1,1,3,1,1,1,1,1,1,1,3,1,1,1,1,1,1,1,1,1,1,1,1,1,3,1,1,1,1,1,1,1,3,</column>
<column index="19">2,2,2,2,2,2,2,2,2,2,2,2,2,2,2,2,2,2,2,2,2,2,2,1,2,2,2,2,2,2,2,2,2,3,2,2,2,2,2,2,2,2,2,2,2,2,2,2,2,2,2,2,2,2,2,2,2,2,2,2,2,2,2,2,2,2,2,3,2,2,2,2,2,2,2,3,2,2,2,2,2,2,2,2,2,2,2,2,2,2,1,2,2,2,2,2,2,2,2,2,</column>
<column index="20">1,1,1,1,1,1,1,1,1,1,1,1,1,1,1,1,1,1,1,1,1,1,1,1,1,1,1,1,1,0,1,0,1,1,1,1,1,1,1,1,1,1,1,1,1,1,1,1,1,1,1,1,1,1,1,1,1,1,1,1,1,1,1,1,1,1,1,1,1,1,1,1,1,1,1,1,1,1,1,1,1,1,1,1,1,1,1,1,1,1,1,1,1,1,1,1,1,0,1,1,</column>
<column index="21">3,2,3,3,3,3,3,3,3,3,3,3,2,3,3,3,3,3,3,3,3,3,3,3,3,3,3,3,3,3,3,3,3,3,3,3,3,3,3,3,3,3,3,3,3,3,3,3,3,3,3,3,3,3,2,3,3,3,3,2,3,3,2,3,3,2,3,3,3,3,3,3,3,3,3,3,3,3,3,3,3,3,3,3,3,3,3,3,3,3,3,3,3,3,3,3,2,3,3,3,</column>
<column index="22">1,1,1,1,1,1,1,1,1,1,2,2,1,1,1,1,1,1,2,1,1,1,1,2,2,1,2,1,1,1,1,1,1,1,1,1,2,1,1,1,1,1,2,1,1,1,1,2,1,1,1,1,2,3,1,1,1,1,1,1,2,1,1,2,1,1,1,1,1,1,1,1,1,1,1,1,1,1,1,1,1,2,1,1,2,1,2,1,1,2,2,1,1,1,1,2,1,1,1,1,</column>
<column index="23">2,2,2,2,2,2,2,2,2,2,2,2,2,2,2,2,2,2,2,2,2,2,2,2,2,2,2,2,2,2,2,2,2,2,2,2,2,2,2,2,2,2,2,2,2,2,2,2,2,2,2,2,2,2,2,2,2,2,2,2,2,2,2,2,2,0,2,2,2,2,2,2,2,2,2,2,2,2,2,2,2,2,2,2,2,2,2,2,2,2,2,2,2,2,2,2,2,2,2,2,</column>
<column index="24">2,2,2,2,2,2,2,2,2,2,2,2,2,2,2,2,2,2,2,2,2,2,2,2,2,2,2,2,2,2,2,2,2,2,2,2,2,2,2,2,2,2,2,2,2,2,2,2,2,2,2,2,2,2,2,2,2,2,2,2,2,2,2,2,2,2,2,2,2,2,2,0,2,2,2,2,2,2,2,2,2,2,2,2,2,2,2,2,2,2,2,2,2,2,2,2,2,2,2,2,</column>
<column index="25">3,0,0,0,3,0,0,0,0,0,0,0,0,0,3,0,0,3,0,0,0,0,0,0,0,0,0,0,0,0,0,0,0,0,0,3,0,0,0,0,0,0,0,0,0,0,0,0,0,0,0,0,0,0,0,0,0,0,0,0,0,0,0,0,0,0,0,0,0,3,0,0,0,0,0,0,0,3,0,0,0,0,0,0,0,0,0,0,0,0,0,3,0,0,0,0,0,0,0,3,</column>
<column index="26">2,3,3,3,2,3,3,3,3,3,3,3,3,2,2,3,3,2,3,3,3,2,3,3,3,3,3,2,3,3,3,3,2,3,3,2,3,2,3,3,3,3,3,3,3,3,3,3,3,2,2,3,3,3,3,2,3,2,3,3,3,3,3,3,3,3,3,3,2,2,3,3,3,3,3,3,3,2,2,3,3,3,3,3,3,3,3,2,3,3,3,2,2,3,3,3,3,3,2,2,</column>
<column index="27">0,0,0,0,0,0,0,0,0,0,0,0,0,0,0,0,0,0,0,0,0,0,0,0,0,0,0,0,0,0,0,0,0,0,0,0,0,0,0,0,0,0,0,0,0,0,0,0,0,0,0,0,0,0,0,0,0,0,0,0,0,0,0,0,0,0,0,0,0,0,0,0,0,0,0,0,0,0,0,0,0,0,0,0,0,0,0,0,0,0,0,2,0,0,0,0,0,0,0,0,</column>
<column index="28">0,0,0,0,0,0,0,0,0,0,2,0,0,0,0,0,0,0,0,0,0,0,0,0,0,0,0,0,0,0,0,0,0,0,0,0,0,0,0,0,0,0,0,0,0,0,0,0,0,0,0,0,0,0,0,0,0,0,0,0,0,0,0,0,0,0,0,0,0,0,0,0,0,0,0,0,0,0,0,0,0,0,0,0,0,0,2,0,0,0,0,0,0,0,0,0,0,0,0,0,</column>
</columns>
</alignment>
</ACGDataFile>
