<?xml version="1.0" encoding="UTF-8" standalone="no"?>
<graphml>
<graph rangemax="50000" rangemin="0">
<node height="2.6442531135394823E-5" id="27">
<annotation key="c_nodes">13: 0-50000[6][5]
</annotation>
</node>
<node height="5.231116097080421E-5" id="24">
<annotation key="c_nodes">16: 0-50000[13][20]
</annotation>
</node>
<node height="2.5870158082505468E-5" id="3558">
<annotation key="c_nodes">20: 0-50000[3][1]
</annotation>
</node>
<node height="3.463296845008219E-5" id="26">
<annotation key="c_nodes">17: 0-50000[4][2]
</annotation>
</node>
<node height="0.0021838801629241265" id="16828">
<annotation key="c_nodes">37: 39680-39826[38][69]
14: 39826-41211[41][72]
35: 41211-41263[53][8]
62: 41263-41409[73][28]
30: 41409-41494[42][48]
52: 41494-50000[42][56]
</annotation>
</node>
<node height="1.0895727347616856E-4" id="30">
<annotation key="c_nodes">72: 0-41211[7][8]
61: 41494-50000[10][8]
</annotation>
</node>
<node height="1.694729720007231E-4" id="1404">
<annotation key="c_nodes">68: 0-18640[9][10]
24: 18640-41211[12][10]
19: 41211-41494[12][23]
40: 41494-50000[12][7]
</annotation>
</node>
<node height="2.517307951359036E-4" id="4332">
<annotation key="c_nodes">50: 0-16482[31][68]
47: 16482-18640[43][68]
15: 18640-22767[69][24]
</annotation>
</node>
<node height="1.0972699517440917E-4" id="1224">
<annotation key="c_nodes">49: 0-18640[18][17]
42: 18640-50000[16][17]
</annotation>
</node>
<node height="1.9008079826241962E-4" id="1334">
<annotation key="c_nodes">51: 41409-41494[19][0]
65: 41494-50000[40][0]
</annotation>
</node>
<node height="4.813728718200843E-5" id="36">
<annotation key="c_nodes">12: 18640-50000[9][11]
</annotation>
</node>
<node height="0.029420830208520574" id="19492">
<annotation key="c_nodes">33: 16482-16566[47][0]
</annotation>
</node>
<node height="0.0010935252457426178" id="15280">
<annotation key="c_nodes">66: 16566-18640[47][0]
46: 18640-22767[15][0]
57: 22767-39680[24][26]
38: 39680-39826[24][0]
41: 39826-41211[24][73]
53: 41211-41263[19][73]
</annotation>
</node>
<node height="5.286047553830068E-5" id="1912">
<annotation key="c_nodes">23: 41211-41494[10][7]
</annotation>
</node>
<node height="1.0207865108345289E-4" id="82">
<annotation key="c_nodes">X</annotation>
</node>
<node height="4.769847817552227E-4" id="18272">
<annotation key="c_nodes">26: 22767-39680[0][69]
73: 39826-41409[0][42]
</annotation>
</node>
<node height="4.527053792396702E-4" id="766">
<annotation key="c_nodes">28: 41263-41409[19][8]
48: 41409-41494[51][8]
56: 41494-50000[65][61]
</annotation>
</node>
<node height="5.712988057046777E-5" id="28">
<annotation key="c_nodes">18: 0-18640[16][11]
</annotation>
</node>
<node height="3.121353302608876E-4" id="2230">
<annotation key="c_nodes">X</annotation>
</node>
<node height="1.9011402798450953E-4" id="1090">
<annotation key="c_nodes">31: 0-16482[22][72]
43: 16482-18640[49][72]
69: 18640-39826[42][72]
</annotation>
</node>
<node height="1.7413526201846033E-4" id="1902">
<annotation key="c_nodes">22: 0-16482[0][49]
</annotation>
</node>
<node height="1.9573479753467841E-4" id="1403"/>
<node height="9.292761530213485E-5" id="1911"/>
<node height="4.60369324970251E-5" id="1259"/>
<node height="8.241209637374988E-4" id="3073"/>
<node height="2.8688873011012464E-5" id="1089"/>
<node height="2.487842442653662E-4" id="231"/>
<node height="4.2547306309312686E-4" id="4857"/>
<node height="1.4503708440309305E-5" id="1223"/>
<node height="1.8194596623655757E-4" id="447"/>
<node height="1.3566346099552477E-4" id="1901"/>
<node height="0.0" id="GS21737_chrX.tsv"/>
<node height="0.0" id="GS20850_chrX.tsv"/>
<node height="0.0" id="GS20510_chrX.tsv"/>
<node height="0.0" id="GS07357_chrX.tsv"/>
<node height="0.0" id="GS18558_chrX.tsv"/>
<node height="0.0" id="GS19649_chrX.tsv"/>
<node height="0.0" id="GS19670_chrX.tsv"/>
<node height="0.0" id="GS18501_chrX.tsv"/>
<node height="0.0" id="GS19025_chrX.tsv"/>
<node height="0.0" id="GS20846_chrX.tsv"/>
<node height="0.0" id="GS18940_chrX.tsv"/>
<node height="0.0" id="GS20845_chrX.tsv"/>
<edge id="edge0" source="GS19670_chrX.tsv" target="27"/>
<edge id="edge1" source="GS19649_chrX.tsv" target="27"/>
<edge id="edge2" source="27" target="24"/>
<edge id="edge3" source="3558" target="24"/>
<edge id="edge4" source="24" target="28"/>
<edge id="edge5" source="GS07357_chrX.tsv" target="3558"/>
<edge id="edge6" source="GS20850_chrX.tsv" target="3558"/>
<edge id="edge7" source="GS18558_chrX.tsv" target="26"/>
<edge id="edge8" source="GS20510_chrX.tsv" target="26"/>
<edge id="edge9" source="26" target="1224"/>
<edge id="edge10" source="15280" target="16828"/>
<edge id="edge11" source="766" target="16828"/>
<edge id="edge12" source="16828" target="19492"/>
<edge id="edge13" source="82" target="30"/>
<edge id="edge14" source="GS19025_chrX.tsv" target="30"/>
<edge id="edge15" source="30" target="1090"/>
<edge id="edge16" source="36" target="1404"/>
<edge id="edge17" source="1912" target="1404"/>
<edge id="edge18" source="1404" target="1334"/>
<edge id="edge19" source="1403" target="4332">
<range>
<start>0</start>
<end>22767</end>
</range>
</edge>
<edge id="edge20" source="1334" target="4332"/>
<edge id="edge21" source="4332" target="4857"/>
<edge id="edge22" source="28" target="1224"/>
<edge id="edge23" source="1224" target="1902"/>
<edge id="edge24" source="1911" target="1334">
<range>
<start>41409</start>
<end>50000</end>
</range>
</edge>
<edge id="edge25" source="GS20846_chrX.tsv" target="36"/>
<edge id="edge26" source="1223" target="36">
<range>
<start>18640</start>
<end>50000</end>
</range>
</edge>
<edge id="edge27" source="3073" target="19492">
<range>
<start>0</start>
<end>16566</end>
</range>
</edge>
<edge id="edge28" source="3073" target="15280">
<range>
<start>16566</start>
<end>50000</end>
</range>
</edge>
<edge id="edge29" source="18272" target="15280"/>
<edge id="edge30" source="1259" target="1912">
<range>
<start>0</start>
<end>41494</end>
</range>
</edge>
<edge id="edge31" source="1089" target="1912">
<range>
<start>41211</start>
<end>50000</end>
</range>
</edge>
<edge id="edge32" source="1259" target="82">
<range>
<start>41494</start>
<end>50000</end>
</range>
</edge>
<edge id="edge33" source="1089" target="82">
<range>
<start>0</start>
<end>41211</end>
</range>
</edge>
<edge id="edge34" source="1901" target="18272">
<range>
<start>16482</start>
<end>50000</end>
</range>
</edge>
<edge id="edge35" source="2230" target="18272"/>
<edge id="edge36" source="4857" target="766">
<range>
<start>41263</start>
<end>50000</end>
</range>
</edge>
<edge id="edge37" source="231" target="766">
<range>
<start>39680</start>
<end>50000</end>
</range>
</edge>
<edge id="edge38" source="1223" target="28">
<range>
<start>0</start>
<end>18640</end>
</range>
</edge>
<edge id="edge39" source="231" target="2230">
<range>
<start>0</start>
<end>39680</end>
</range>
</edge>
<edge id="edge40" source="447" target="2230">
<range>
<start>39826</start>
<end>50000</end>
</range>
</edge>
<edge id="edge41" source="447" target="1090">
<range>
<start>0</start>
<end>39826</end>
</range>
</edge>
<edge id="edge42" source="1090" target="1403"/>
<edge id="edge43" source="1901" target="1902">
<range>
<start>0</start>
<end>16482</end>
</range>
</edge>
<edge id="edge44" source="1902" target="447"/>
<edge id="edge45" source="1403" target="231">
<range>
<start>22767</start>
<end>50000</end>
</range>
</edge>
<edge id="edge46" source="GS21737_chrX.tsv" target="1911"/>
<edge id="edge47" source="1911" target="1901">
<range>
<start>0</start>
<end>41409</end>
</range>
</edge>
<edge id="edge48" source="GS18940_chrX.tsv" target="1259"/>
<edge id="edge49" source="4857" target="3073">
<range>
<start>0</start>
<end>41263</end>
</range>
</edge>
<edge id="edge50" source="GS18501_chrX.tsv" target="1089"/>
<edge id="edge51" source="GS20845_chrX.tsv" target="1223"/>
</graph>
</graphml>
